{
    "Meta Data": {
        "1. Information": "Batch Stock Market Quotes",
        "2. Notes": "IEX Real-Time Price provided for free by IEX (https://iextrading.com/developer/).",
        "3. Time Zone": "US/Eastern"
    },
    "Stock Quotes": [
        {
            "1. symbol": "TSLA",
            "2. price": "322.9150",
            "3. volume": "9402933",
            "4. timestamp": "2018-06-07 12:16:05"
        },
        {
            "1. symbol": "AAPL",
            "2. price": "193.1700",
            "3. volume": "8325806",
            "4. timestamp": "2018-06-07 12:16:06"
        },
        {
            "1. symbol": "MSFT",
            "2. price": "101.4400",
            "3. volume": "10495148",
            "4. timestamp": "2018-06-07 12:16:06"
        },
        {
            "1. symbol": "MCD",
            "2. price": "167.8800",
            "3. volume": "2735491",
            "4. timestamp": "2018-06-07 12:16:05"
        },
        {
            "1. symbol": "NKE",
            "2. price": "75.4700",
            "3. volume": "2507261",
            "4. timestamp": "2018-06-07 12:16:00"
        },
        {
            "1. symbol": "PFE",
            "2. price": "36.5000",
            "3. volume": "5840882",
            "4. timestamp": "2018-06-07 12:16:02"
        },
        {
            "1. symbol": "FB",
            "2. price": "187.8400",
            "3. volume": "12354430",
            "4. timestamp": "2018-06-07 12:16:06"
        },
        {
            "1. symbol": "GOOGL",
            "2. price": "1135.3800",
            "3. volume": "873650",
            "4. timestamp": "2018-06-07 12:16:06"
        },
        {
            "1. symbol": "GS",
            "2. price": "234.7200",
            "3. volume": "1454812",
            "4. timestamp": "2018-06-07 12:16:03"
        },
        {
            "1. symbol": "LMT",
            "2. price": "321.4000",
            "3. volume": "256599",
            "4. timestamp": "2018-06-07 12:16:02"
        }
    ]
}