{
    "Meta Data": {
        "1. Information": "Batch Stock Market Quotes",
        "2. Notes": "IEX Real-Time Price provided for free by IEX (https://iextrading.com/developer/).",
        "3. Time Zone": "US/Eastern"
    },
    "Stock Quotes": [
        {
            "1. symbol": "TSLA",
            "2. price": "344.0250",
            "3. volume": "4756686",
            "4. timestamp": "2018-06-12 10:14:49"
        },
        {
            "1. symbol": "AAPL",
            "2. price": "191.7400",
            "3. volume": "3036133",
            "4. timestamp": "2018-06-12 10:14:47"
        },
        {
            "1. symbol": "MSFT",
            "2. price": "101.1500",
            "3. volume": "2560524",
            "4. timestamp": "2018-06-12 10:14:46"
        },
        {
            "1. symbol": "MCD",
            "2. price": "166.6800",
            "3. volume": "388945",
            "4. timestamp": "2018-06-12 10:14:38"
        },
        {
            "1. symbol": "NKE",
            "2. price": "74.4300",
            "3. volume": "606506",
            "4. timestamp": "2018-06-12 10:14:46"
        },
        {
            "1. symbol": "PFE",
            "2. price": "36.2450",
            "3. volume": "1834476",
            "4. timestamp": "2018-06-12 10:14:46"
        },
        {
            "1. symbol": "FB",
            "2. price": "192.1300",
            "3. volume": "2270384",
            "4. timestamp": "2018-06-12 10:14:44"
        },
        {
            "1. symbol": "GOOGL",
            "2. price": "1147.0700",
            "3. volume": "223304",
            "4. timestamp": "2018-06-12 10:14:24"
        },
        {
            "1. symbol": "GS",
            "2. price": "234.8900",
            "3. volume": "221906",
            "4. timestamp": "2018-06-12 10:14:33"
        },
        {
            "1. symbol": "LMT",
            "2. price": "314.0450",
            "3. volume": "369727",
            "4. timestamp": "2018-06-12 10:14:21"
        }
    ]
}