{
    "Meta Data": {
        "1. Information": "Batch Stock Market Quotes",
        "2. Notes": "IEX Real-Time Price provided for free by IEX (https://iextrading.com/developer/).",
        "3. Time Zone": "US/Eastern"
    },
    "Stock Quotes": [
        {
            "1. symbol": "TSLA",
            "2. price": "357.8200",
            "3. volume": "9294908",
            "4. timestamp": "2018-06-14 15:26:14"
        },
        {
            "1. symbol": "AAPL",
            "2. price": "190.8750",
            "3. volume": "14960270",
            "4. timestamp": "2018-06-14 15:26:14"
        },
        {
            "1. symbol": "MSFT",
            "2. price": "101.3550",
            "3. volume": "16399092",
            "4. timestamp": "2018-06-14 15:26:14"
        },
        {
            "1. symbol": "MCD",
            "2. price": "167.0600",
            "3. volume": "1293197",
            "4. timestamp": "2018-06-14 15:26:13"
        },
        {
            "1. symbol": "NKE",
            "2. price": "74.6800",
            "3. volume": "2734001",
            "4. timestamp": "2018-06-14 15:25:59"
        },
        {
            "1. symbol": "PFE",
            "2. price": "36.1500",
            "3. volume": "12385064",
            "4. timestamp": "2018-06-14 15:26:06"
        },
        {
            "1. symbol": "FB",
            "2. price": "196.6100",
            "3. volume": "14204363",
            "4. timestamp": "2018-06-14 15:26:15"
        },
        {
            "1. symbol": "GOOGL",
            "2. price": "1159.8700",
            "3. volume": "1359685",
            "4. timestamp": "2018-06-14 15:26:14"
        },
        {
            "1. symbol": "GS",
            "2. price": "233.7800",
            "3. volume": "2213556",
            "4. timestamp": "2018-06-14 15:26:15"
        },
        {
            "1. symbol": "LMT",
            "2. price": "311.1800",
            "3. volume": "904443",
            "4. timestamp": "2018-06-14 15:26:13"
        }
    ]
}