{
    "Meta Data": {
        "1. Information": "Batch Stock Market Quotes",
        "2. Notes": "IEX Real-Time Price provided for free by IEX (https://iextrading.com/developer/).",
        "3. Time Zone": "US/Eastern"
    },
    "Stock Quotes": [
        {
            "1. symbol": "TSLA",
            "2. price": "326.5300",
            "3. volume": "4000295",
            "4. timestamp": "2018-06-07 09:56:49"
        },
        {
            "1. symbol": "AAPL",
            "2. price": "193.9300",
            "3. volume": "2548405",
            "4. timestamp": "2018-06-07 09:56:50"
        },
        {
            "1. symbol": "MSFT",
            "2. price": "102.2550",
            "3. volume": "2154891",
            "4. timestamp": "2018-06-07 09:56:50"
        },
        {
            "1. symbol": "MCD",
            "2. price": "165.6500",
            "3. volume": "676426",
            "4. timestamp": "2018-06-07 09:56:45"
        },
        {
            "1. symbol": "NKE",
            "2. price": "74.8400",
            "3. volume": "420036",
            "4. timestamp": "2018-06-07 09:56:50"
        },
        {
            "1. symbol": "PFE",
            "2. price": "36.4650",
            "3. volume": "1031625",
            "4. timestamp": "2018-06-07 09:56:49"
        },
        {
            "1. symbol": "FB",
            "2. price": "189.6150",
            "3. volume": "2849844",
            "4. timestamp": "2018-06-07 09:56:50"
        },
        {
            "1. symbol": "GOOGL",
            "2. price": "1141.9900",
            "3. volume": "226466",
            "4. timestamp": "2018-06-07 09:56:41"
        },
        {
            "1. symbol": "GS",
            "2. price": "235.0600",
            "3. volume": "449294",
            "4. timestamp": "2018-06-07 09:56:45"
        },
        {
            "1. symbol": "LMT",
            "2. price": "320.5300",
            "3. volume": "68658",
            "4. timestamp": "2018-06-07 09:56:40"
        }
    ]
}