{
    "Meta Data": {
        "1. Information": "Batch Stock Market Quotes",
        "2. Notes": "IEX Real-Time Price provided for free by IEX (https://iextrading.com/developer/).",
        "3. Time Zone": "US/Eastern"
    },
    "Stock Quotes": [
        {
            "1. symbol": "TSLA",
            "2. price": "355.2400",
            "3. volume": "8581933",
            "4. timestamp": "2018-06-14 15:05:49"
        },
        {
            "1. symbol": "AAPL",
            "2. price": "190.7200",
            "3. volume": "14271120",
            "4. timestamp": "2018-06-14 15:05:49"
        },
        {
            "1. symbol": "MSFT",
            "2. price": "101.1900",
            "3. volume": "15617580",
            "4. timestamp": "2018-06-14 15:05:49"
        },
        {
            "1. symbol": "MCD",
            "2. price": "166.8500",
            "3. volume": "1193511",
            "4. timestamp": "2018-06-14 15:05:48"
        },
        {
            "1. symbol": "NKE",
            "2. price": "74.5400",
            "3. volume": "2438598",
            "4. timestamp": "2018-06-14 15:05:48"
        },
        {
            "1. symbol": "PFE",
            "2. price": "36.0900",
            "3. volume": "11693599",
            "4. timestamp": "2018-06-14 15:05:49"
        },
        {
            "1. symbol": "FB",
            "2. price": "196.4400",
            "3. volume": "13637203",
            "4. timestamp": "2018-06-14 15:05:49"
        },
        {
            "1. symbol": "GOOGL",
            "2. price": "1157.2750",
            "3. volume": "1315909",
            "4. timestamp": "2018-06-14 15:05:49"
        },
        {
            "1. symbol": "GS",
            "2. price": "233.4700",
            "3. volume": "2157562",
            "4. timestamp": "2018-06-14 15:05:48"
        },
        {
            "1. symbol": "LMT",
            "2. price": "310.8200",
            "3. volume": "847823",
            "4. timestamp": "2018-06-14 15:05:49"
        }
    ]
}