{
    "Meta Data": {
        "1. Information": "Batch Stock Market Quotes",
        "2. Notes": "IEX Real-Time Price provided for free by IEX (https://iextrading.com/developer/).",
        "3. Time Zone": "US/Eastern"
    },
    "Stock Quotes": [
        {
            "1. symbol": "TSLA",
            "2. price": "319.5100",
            "3. volume": "17991095",
            "4. timestamp": "2018-06-06 15:54:03"
        },
        {
            "1. symbol": "AAPL",
            "2. price": "193.8950",
            "3. volume": "16107480",
            "4. timestamp": "2018-06-06 15:54:03"
        },
        {
            "1. symbol": "MSFT",
            "2. price": "102.4400",
            "3. volume": "14605428",
            "4. timestamp": "2018-06-06 15:54:03"
        },
        {
            "1. symbol": "MCD",
            "2. price": "162.2300",
            "3. volume": "2523623",
            "4. timestamp": "2018-06-06 15:54:03"
        },
        {
            "1. symbol": "NKE",
            "2. price": "74.6850",
            "3. volume": "3920115",
            "4. timestamp": "2018-06-06 15:54:04"
        },
        {
            "1. symbol": "PFE",
            "2. price": "36.3050",
            "3. volume": "13790681",
            "4. timestamp": "2018-06-06 15:53:53"
        },
        {
            "1. symbol": "FB",
            "2. price": "191.4700",
            "3. volume": "19201976",
            "4. timestamp": "2018-06-06 15:54:03"
        },
        {
            "1. symbol": "GOOGL",
            "2. price": "1147.4700",
            "3. volume": "1393538",
            "4. timestamp": "2018-06-06 15:53:43"
        },
        {
            "1. symbol": "GS",
            "2. price": "232.0400",
            "3. volume": "2142229",
            "4. timestamp": "2018-06-06 15:54:00"
        },
        {
            "1. symbol": "LMT",
            "2. price": "319.4200",
            "3. volume": "808301",
            "4. timestamp": "2018-06-06 15:53:13"
        }
    ]
}