{
    "Meta Data": {
        "1. Information": "Batch Stock Market Quotes",
        "2. Notes": "IEX Real-Time Price provided for free by IEX (https://iextrading.com/developer/).",
        "3. Time Zone": "US/Eastern"
    },
    "Stock Quotes": [
        {
            "1. symbol": "TSLA",
            "2. price": "345.5950",
            "3. volume": "3438508",
            "4. timestamp": "2018-06-13 10:29:09"
        },
        {
            "1. symbol": "AAPL",
            "2. price": "192.3750",
            "3. volume": "3374745",
            "4. timestamp": "2018-06-13 10:29:09"
        },
        {
            "1. symbol": "MSFT",
            "2. price": "101.5200",
            "3. volume": "6018445",
            "4. timestamp": "2018-06-13 10:29:10"
        },
        {
            "1. symbol": "MCD",
            "2. price": "167.0200",
            "3. volume": "485098",
            "4. timestamp": "2018-06-13 10:29:08"
        },
        {
            "1. symbol": "NKE",
            "2. price": "74.6600",
            "3. volume": "648976",
            "4. timestamp": "2018-06-13 10:29:10"
        },
        {
            "1. symbol": "PFE",
            "2. price": "36.4000",
            "3. volume": "2247362",
            "4. timestamp": "2018-06-13 10:29:08"
        },
        {
            "1. symbol": "FB",
            "2. price": "192.8900",
            "3. volume": "2450389",
            "4. timestamp": "2018-06-13 10:29:09"
        },
        {
            "1. symbol": "GOOGL",
            "2. price": "1150.9900",
            "3. volume": "413981",
            "4. timestamp": "2018-06-13 10:28:42"
        },
        {
            "1. symbol": "GS",
            "2. price": "234.3300",
            "3. volume": "563142",
            "4. timestamp": "2018-06-13 10:28:58"
        },
        {
            "1. symbol": "LMT",
            "2. price": "315.9250",
            "3. volume": "523661",
            "4. timestamp": "2018-06-13 10:28:39"
        }
    ]
}