{
    "Meta Data": {
        "1. Information": "Batch Stock Market Quotes",
        "2. Notes": "IEX Real-Time Price provided for free by IEX (https://iextrading.com/developer/).",
        "3. Time Zone": "US/Eastern"
    },
    "Stock Quotes": [
        {
            "1. symbol": "TSLA",
            "2. price": "346.1250",
            "3. volume": "7135110",
            "4. timestamp": "2018-06-12 11:06:35"
        },
        {
            "1. symbol": "AAPL",
            "2. price": "191.4600",
            "3. volume": "4946957",
            "4. timestamp": "2018-06-12 11:06:31"
        },
        {
            "1. symbol": "MSFT",
            "2. price": "101.3300",
            "3. volume": "4548078",
            "4. timestamp": "2018-06-12 11:06:31"
        },
        {
            "1. symbol": "MCD",
            "2. price": "166.6400",
            "3. volume": "826445",
            "4. timestamp": "2018-06-12 11:06:17"
        },
        {
            "1. symbol": "NKE",
            "2. price": "74.2900",
            "3. volume": "1049712",
            "4. timestamp": "2018-06-12 11:06:37"
        },
        {
            "1. symbol": "PFE",
            "2. price": "36.2450",
            "3. volume": "3518978",
            "4. timestamp": "2018-06-12 11:06:38"
        },
        {
            "1. symbol": "FB",
            "2. price": "192.2000",
            "3. volume": "3548768",
            "4. timestamp": "2018-06-12 11:06:32"
        },
        {
            "1. symbol": "GOOGL",
            "2. price": "1143.9300",
            "3. volume": "377250",
            "4. timestamp": "2018-06-12 11:06:18"
        },
        {
            "1. symbol": "GS",
            "2. price": "233.0450",
            "3. volume": "471040",
            "4. timestamp": "2018-06-12 11:06:32"
        },
        {
            "1. symbol": "LMT",
            "2. price": "314.7000",
            "3. volume": "577402",
            "4. timestamp": "2018-06-12 11:06:13"
        }
    ]
}