{
    "Meta Data": {
        "1. Information": "Batch Stock Market Quotes",
        "2. Notes": "IEX Real-Time Price provided for free by IEX (https://iextrading.com/developer/).",
        "3. Time Zone": "US/Eastern"
    },
    "Stock Quotes": [
        {
            "1. symbol": "TSLA",
            "2. price": "340.5600",
            "3. volume": "3356324",
            "4. timestamp": "2018-06-12 09:49:25"
        },
        {
            "1. symbol": "AAPL",
            "2. price": "191.4900",
            "3. volume": "1716029",
            "4. timestamp": "2018-06-12 09:49:24"
        },
        {
            "1. symbol": "MSFT",
            "2. price": "101.3100",
            "3. volume": "1533124",
            "4. timestamp": "2018-06-12 09:49:22"
        },
        {
            "1. symbol": "MCD",
            "2. price": "166.8000",
            "3. volume": "225872",
            "4. timestamp": "2018-06-12 09:49:24"
        },
        {
            "1. symbol": "NKE",
            "2. price": "74.2600",
            "3. volume": "309846",
            "4. timestamp": "2018-06-12 09:49:09"
        },
        {
            "1. symbol": "PFE",
            "2. price": "36.3500",
            "3. volume": "1086735",
            "4. timestamp": "2018-06-12 09:49:24"
        },
        {
            "1. symbol": "FB",
            "2. price": "192.6500",
            "3. volume": "1496184",
            "4. timestamp": "2018-06-12 09:49:22"
        },
        {
            "1. symbol": "GOOGL",
            "2. price": "1147.8800",
            "3. volume": "161802",
            "4. timestamp": "2018-06-12 09:49:22"
        },
        {
            "1. symbol": "GS",
            "2. price": "234.5700",
            "3. volume": "159851",
            "4. timestamp": "2018-06-12 09:49:25"
        },
        {
            "1. symbol": "LMT",
            "2. price": "313.6600",
            "3. volume": "164021",
            "4. timestamp": "2018-06-12 09:49:17"
        }
    ]
}