{
    "Meta Data": {
        "1. Information": "Batch Stock Market Quotes",
        "2. Notes": "IEX Real-Time Price provided for free by IEX (https://iextrading.com/developer/).",
        "3. Time Zone": "US/Eastern"
    },
    "Stock Quotes": [
        {
            "1. symbol": "TSLA",
            "2. price": "346.1600",
            "3. volume": "5432532",
            "4. timestamp": "2018-06-12 10:24:59"
        },
        {
            "1. symbol": "AAPL",
            "2. price": "191.5700",
            "3. volume": "3553173",
            "4. timestamp": "2018-06-12 10:24:58"
        },
        {
            "1. symbol": "MSFT",
            "2. price": "101.1300",
            "3. volume": "2991566",
            "4. timestamp": "2018-06-12 10:24:56"
        },
        {
            "1. symbol": "MCD",
            "2. price": "166.8400",
            "3. volume": "464588",
            "4. timestamp": "2018-06-12 10:24:56"
        },
        {
            "1. symbol": "NKE",
            "2. price": "74.3400",
            "3. volume": "687707",
            "4. timestamp": "2018-06-12 10:24:59"
        },
        {
            "1. symbol": "PFE",
            "2. price": "36.1500",
            "3. volume": "2178952",
            "4. timestamp": "2018-06-12 10:24:59"
        },
        {
            "1. symbol": "FB",
            "2. price": "192.1800",
            "3. volume": "2530403",
            "4. timestamp": "2018-06-12 10:24:59"
        },
        {
            "1. symbol": "GOOGL",
            "2. price": "1145.0200",
            "3. volume": "264952",
            "4. timestamp": "2018-06-12 10:24:56"
        },
        {
            "1. symbol": "GS",
            "2. price": "234.3600",
            "3. volume": "254866",
            "4. timestamp": "2018-06-12 10:24:54"
        },
        {
            "1. symbol": "LMT",
            "2. price": "314.5200",
            "3. volume": "416856",
            "4. timestamp": "2018-06-12 10:24:49"
        }
    ]
}