{
    "Meta Data": {
        "1. Information": "Batch Stock Market Quotes",
        "2. Notes": "IEX Real-Time Price provided for free by IEX (https://iextrading.com/developer/).",
        "3. Time Zone": "US/Eastern"
    },
    "Stock Quotes": [
        {
            "1. symbol": "TSLA",
            "2. price": "357.8300",
            "3. volume": "9555604",
            "4. timestamp": "2018-06-14 15:32:40"
        },
        {
            "1. symbol": "AAPL",
            "2. price": "190.9100",
            "3. volume": "15187757",
            "4. timestamp": "2018-06-14 15:32:44"
        },
        {
            "1. symbol": "MSFT",
            "2. price": "101.3600",
            "3. volume": "16723962",
            "4. timestamp": "2018-06-14 15:32:45"
        },
        {
            "1. symbol": "MCD",
            "2. price": "167.1500",
            "3. volume": "1331692",
            "4. timestamp": "2018-06-14 15:32:41"
        },
        {
            "1. symbol": "NKE",
            "2. price": "74.7800",
            "3. volume": "2872710",
            "4. timestamp": "2018-06-14 15:32:41"
        },
        {
            "1. symbol": "PFE",
            "2. price": "36.1950",
            "3. volume": "12637421",
            "4. timestamp": "2018-06-14 15:32:40"
        },
        {
            "1. symbol": "FB",
            "2. price": "196.8000",
            "3. volume": "14410588",
            "4. timestamp": "2018-06-14 15:32:44"
        },
        {
            "1. symbol": "GOOGL",
            "2. price": "1161.3200",
            "3. volume": "1383964",
            "4. timestamp": "2018-06-14 15:32:37"
        },
        {
            "1. symbol": "GS",
            "2. price": "233.6500",
            "3. volume": "2239760",
            "4. timestamp": "2018-06-14 15:32:38"
        },
        {
            "1. symbol": "LMT",
            "2. price": "311.0100",
            "3. volume": "917292",
            "4. timestamp": "2018-06-14 15:31:56"
        }
    ]
}