{
    "Meta Data": {
        "1. Information": "Batch Stock Market Quotes",
        "2. Notes": "IEX Real-Time Price provided for free by IEX (https://iextrading.com/developer/).",
        "3. Time Zone": "US/Eastern"
    },
    "Stock Quotes": [
        {
            "1. symbol": "TSLA",
            "2. price": "360.9100",
            "3. volume": "7225481",
            "4. timestamp": "2018-06-15 13:02:56"
        },
        {
            "1. symbol": "AAPL",
            "2. price": "188.8900",
            "3. volume": "21674881",
            "4. timestamp": "2018-06-15 13:02:56"
        },
        {
            "1. symbol": "MSFT",
            "2. price": "100.9350",
            "3. volume": "23989208",
            "4. timestamp": "2018-06-15 13:02:57"
        },
        {
            "1. symbol": "MCD",
            "2. price": "165.6200",
            "3. volume": "2868951",
            "4. timestamp": "2018-06-15 13:02:31"
        },
        {
            "1. symbol": "NKE",
            "2. price": "75.3300",
            "3. volume": "4320110",
            "4. timestamp": "2018-06-15 13:02:56"
        },
        {
            "1. symbol": "PFE",
            "2. price": "36.1350",
            "3. volume": "16881905",
            "4. timestamp": "2018-06-15 13:02:52"
        },
        {
            "1. symbol": "FB",
            "2. price": "196.9500",
            "3. volume": "11178872",
            "4. timestamp": "2018-06-15 13:02:57"
        },
        {
            "1. symbol": "GOOGL",
            "2. price": "1157.5000",
            "3. volume": "1113258",
            "4. timestamp": "2018-06-15 13:02:57"
        },
        {
            "1. symbol": "GS",
            "2. price": "231.5200",
            "3. volume": "2823268",
            "4. timestamp": "2018-06-15 13:02:35"
        },
        {
            "1. symbol": "LMT",
            "2. price": "308.6000",
            "3. volume": "674318",
            "4. timestamp": "2018-06-15 13:02:35"
        }
    ]
}