{
    "Meta Data": {
        "1. Information": "Batch Stock Market Quotes",
        "2. Notes": "IEX Real-Time Price provided for free by IEX (https://iextrading.com/developer/).",
        "3. Time Zone": "US/Eastern"
    },
    "Stock Quotes": [
        {
            "1. symbol": "TSLA",
            "2. price": "344.1500",
            "3. volume": "4860136",
            "4. timestamp": "2018-06-12 10:16:51"
        },
        {
            "1. symbol": "AAPL",
            "2. price": "191.8150",
            "3. volume": "3177920",
            "4. timestamp": "2018-06-12 10:16:25"
        },
        {
            "1. symbol": "MSFT",
            "2. price": "101.1950",
            "3. volume": "2645486",
            "4. timestamp": "2018-06-12 10:16:50"
        },
        {
            "1. symbol": "MCD",
            "2. price": "166.6100",
            "3. volume": "402750",
            "4. timestamp": "2018-06-12 10:16:52"
        },
        {
            "1. symbol": "NKE",
            "2. price": "74.4500",
            "3. volume": "624620",
            "4. timestamp": "2018-06-12 10:16:48"
        },
        {
            "1. symbol": "PFE",
            "2. price": "36.2400",
            "3. volume": "1905900",
            "4. timestamp": "2018-06-12 10:16:52"
        },
        {
            "1. symbol": "FB",
            "2. price": "192.0500",
            "3. volume": "2321616",
            "4. timestamp": "2018-06-12 10:16:50"
        },
        {
            "1. symbol": "GOOGL",
            "2. price": "1147.3100",
            "3. volume": "228145",
            "4. timestamp": "2018-06-12 10:16:47"
        },
        {
            "1. symbol": "GS",
            "2. price": "234.6750",
            "3. volume": "226060",
            "4. timestamp": "2018-06-12 10:16:50"
        },
        {
            "1. symbol": "LMT",
            "2. price": "314.9300",
            "3. volume": "385027",
            "4. timestamp": "2018-06-12 10:16:51"
        }
    ]
}