{
    "Meta Data": {
        "1. Information": "Batch Stock Market Quotes",
        "2. Notes": "IEX Real-Time Price provided for free by IEX (https://iextrading.com/developer/).",
        "3. Time Zone": "US/Eastern"
    },
    "Stock Quotes": [
        {
            "1. symbol": "TSLA",
            "2. price": "342.0700",
            "3. volume": "17104709",
            "4. timestamp": "2018-06-12 14:08:45"
        },
        {
            "1. symbol": "AAPL",
            "2. price": "192.2300",
            "3. volume": "10275474",
            "4. timestamp": "2018-06-12 14:08:45"
        },
        {
            "1. symbol": "MSFT",
            "2. price": "101.2100",
            "3. volume": "10014846",
            "4. timestamp": "2018-06-12 14:08:43"
        },
        {
            "1. symbol": "MCD",
            "2. price": "166.7200",
            "3. volume": "1728142",
            "4. timestamp": "2018-06-12 14:08:35"
        },
        {
            "1. symbol": "NKE",
            "2. price": "74.4800",
            "3. volume": "2288193",
            "4. timestamp": "2018-06-12 14:07:27"
        },
        {
            "1. symbol": "PFE",
            "2. price": "36.2650",
            "3. volume": "8551044",
            "4. timestamp": "2018-06-12 14:08:31"
        },
        {
            "1. symbol": "FB",
            "2. price": "193.1400",
            "3. volume": "6997273",
            "4. timestamp": "2018-06-12 14:08:40"
        },
        {
            "1. symbol": "GOOGL",
            "2. price": "1146.1800",
            "3. volume": "712680",
            "4. timestamp": "2018-06-12 14:08:40"
        },
        {
            "1. symbol": "GS",
            "2. price": "232.8300",
            "3. volume": "1072813",
            "4. timestamp": "2018-06-12 14:08:44"
        },
        {
            "1. symbol": "LMT",
            "2. price": "316.0000",
            "3. volume": "1018636",
            "4. timestamp": "2018-06-12 14:07:06"
        }
    ]
}