{
    "Meta Data": {
        "1. Information": "Batch Stock Market Quotes",
        "2. Notes": "IEX Real-Time Price provided for free by IEX (https://iextrading.com/developer/).",
        "3. Time Zone": "US/Eastern"
    },
    "Stock Quotes": [
        {
            "1. symbol": "TSLA",
            "2. price": "317.1400",
            "3. volume": "12168294",
            "4. timestamp": "2018-06-07 14:38:18"
        },
        {
            "1. symbol": "AAPL",
            "2. price": "193.3100",
            "3. volume": "12919005",
            "4. timestamp": "2018-06-07 14:38:22"
        },
        {
            "1. symbol": "MSFT",
            "2. price": "100.7450",
            "3. volume": "17496610",
            "4. timestamp": "2018-06-07 14:38:22"
        },
        {
            "1. symbol": "MCD",
            "2. price": "169.0200",
            "3. volume": "4258923",
            "4. timestamp": "2018-06-07 14:38:22"
        },
        {
            "1. symbol": "NKE",
            "2. price": "75.2600",
            "3. volume": "3855882",
            "4. timestamp": "2018-06-07 14:38:22"
        },
        {
            "1. symbol": "PFE",
            "2. price": "36.5000",
            "3. volume": "9014595",
            "4. timestamp": "2018-06-07 14:38:20"
        },
        {
            "1. symbol": "FB",
            "2. price": "188.1400",
            "3. volume": "16277827",
            "4. timestamp": "2018-06-07 14:38:23"
        },
        {
            "1. symbol": "GOOGL",
            "2. price": "1135.2500",
            "3. volume": "1386068",
            "4. timestamp": "2018-06-07 14:38:15"
        },
        {
            "1. symbol": "GS",
            "2. price": "233.3600",
            "3. volume": "2035531",
            "4. timestamp": "2018-06-07 14:38:23"
        },
        {
            "1. symbol": "LMT",
            "2. price": "320.7200",
            "3. volume": "413090",
            "4. timestamp": "2018-06-07 14:38:21"
        }
    ]
}